assetto_corsa_rl/__init__.py
assetto_corsa_rl/ac_env.py
assetto_corsa_rl/ac_send_actions.py
assetto_corsa_rl/ac_telemetry_helper.py
assetto_corsa_rl/cli.py
assetto_corsa_rl/cli_registry.py
assetto_corsa_rl/env_helper.py
assetto_corsa_rl/load.py
assetto_corsa_rl/model/__init__.py
assetto_corsa_rl/model/noisy.py
assetto_corsa_rl/model/sac.py
assetto_corsa_rl/model/vae.py
assetto_corsa_rl/train/__init__.py
assetto_corsa_rl/train/train_core.py
assetto_corsa_rl/train/train_utils.py
assetto_corsa_rl-0.1.3.dist-info/licenses/LICENSE
assetto_corsa_rl-0.1.3.dist-info/METADATA
assetto_corsa_rl-0.1.3.dist-info/WHEEL
assetto_corsa_rl-0.1.3.dist-info/entry_points.txt
assetto_corsa_rl-0.1.3.dist-info/top_level.txt
assetto_corsa_rl-0.1.3.dist-info/RECORD
