Metadata-Version: 2.4
Name: assetto-corsa-rl
Version: 0.1.3
Summary: Reinforcement Learning toolkit for Assetto Corsa and Car Racing environments
Author: Assetto Corsa RL Contributors
License: MIT
Project-URL: Homepage, https://github.com/yourusername/assetto-corsa-rl
Project-URL: Repository, https://github.com/yourusername/assetto-corsa-rl
Project-URL: Documentation, https://github.com/yourusername/assetto-corsa-rl#readme
Project-URL: Bug Tracker, https://github.com/yourusername/assetto-corsa-rl/issues
Keywords: reinforcement-learning,assetto-corsa,racing,SAC,VAE,deep-learning
Classifier: Development Status :: 3 - Alpha
Classifier: Intended Audience :: Developers
Classifier: Intended Audience :: Science/Research
Classifier: License :: OSI Approved :: MIT License
Classifier: Operating System :: OS Independent
Classifier: Programming Language :: Python :: 3
Classifier: Programming Language :: Python :: 3.9
Classifier: Programming Language :: Python :: 3.10
Classifier: Programming Language :: Python :: 3.11
Classifier: Topic :: Scientific/Engineering :: Artificial Intelligence
Classifier: Topic :: Games/Entertainment :: Simulation
Requires-Python: >=3.9
License-File: LICENSE
Requires-Dist: torch>=2.0.0
Requires-Dist: torchrl>=0.2.0
Requires-Dist: tensordict>=0.2.0
Requires-Dist: gymnasium>=0.29.0
Requires-Dist: numpy>=1.24.0
Requires-Dist: opencv-python>=4.8.0
Requires-Dist: Pillow>=10.0.0
Requires-Dist: matplotlib>=3.7.0
Requires-Dist: click>=8.1.0
Requires-Dist: PyYAML>=6.0
Requires-Dist: lightning>=2.0.0
Requires-Dist: wandb>=0.15.0
Provides-Extra: dev
Requires-Dist: pytest>=7.4.0; extra == "dev"
Requires-Dist: pytest-cov>=4.1.0; extra == "dev"
Requires-Dist: black>=23.7.0; extra == "dev"
Requires-Dist: isort>=5.12.0; extra == "dev"
Requires-Dist: flake8>=6.1.0; extra == "dev"
Requires-Dist: mypy>=1.5.0; extra == "dev"
Dynamic: license-file
